biomeanalyzer/Data_IO.py
biomeanalyzer/Krona.py
biomeanalyzer/LoadDatabase.py
biomeanalyzer/Normalization.py
biomeanalyzer/Stats.py
biomeanalyzer/TaxId.py
biomeanalyzer/__init__.py
biomeanalyzer/load_database.py
biomeanalyzer/data/rrnDB-5.8_pantaxa_stats_NCBI.tsv
biomeanalyzer/data/rrnDB-5.9_pantaxa_stats_NCBI.tsv
biomeanalyzer/data/taxonomy.tsv
biomeanalyzer/io/__init__.py
biomeanalyzer/io/data_preparation.py
biomeanalyzer/io/load_data.py
biomeanalyzer/krona/__init__.py
biomeanalyzer/krona/krona_create.py
biomeanalyzer/legend/__init__.py
biomeanalyzer/legend/legend.py
biomeanalyzer/metaboanalyst_csv/__init__.py
biomeanalyzer/metaboanalyst_csv/data_to_csv.py
biomeanalyzer/metaboanalyst_csv/legend_adding.py
biomeanalyzer/normalization/__init__.py
biomeanalyzer/normalization/copy_normalization.py
biomeanalyzer/stats/__init__.py
biomeanalyzer/stats/ttest_microrganisms.py
io/__init__.py
io/load_data.py
normalization/__init__.py
normalization/copy_normalization.py
biomeanalyzer-0.1.1.dist-info/METADATA
biomeanalyzer-0.1.1.dist-info/WHEEL
biomeanalyzer-0.1.1.dist-info/top_level.txt
biomeanalyzer-0.1.1.dist-info/RECORD
